{
  "_notes": "Raw values fetched from public sources before any calculation. Each entry: { value, unit, source, source_url, last_updated }. placeholder_data.json carries only the calculated dashboard cells; this file is the audit trail.",
  "Maruti": {
    "FY24": {
      "sales_volume_total": {
        "value": 2076711,
        "unit": "units",
        "source": "Maruti monthly sales press release",
        "source_url": "https://www.marutisuzuki.com/corporate/media/press-releases/2024/april/maruti-suzuki-sales-in-march-2024",
        "last_updated": "2026-05-12"
      },
      "sales_volume_domestic": {
        "value": 1793644,
        "unit": "units",
        "source": "Maruti monthly sales press release",
        "source_url": "https://www.marutisuzuki.com/corporate/media/press-releases/2024/april/maruti-suzuki-sales-in-march-2024",
        "last_updated": "2026-05-12"
      },
      "sales_volume_export": {
        "value": 283067,
        "unit": "units",
        "source": "Maruti monthly sales press release",
        "source_url": "https://www.marutisuzuki.com/corporate/media/press-releases/2024/april/maruti-suzuki-sales-in-march-2024",
        "last_updated": "2026-05-12"
      },
      "net_sales_cr": {
        "value": 134938,
        "unit": "₹ Cr",
        "source": "Maruti FY financial results press release",
        "source_url": "https://www.marutisuzuki.com/corporate/media/press-releases/2024/april/maruti-suzuki-announces-financial-results-for-fy2023-24",
        "last_updated": "2026-05-12"
      },
      "pat_cr": {
        "value": 13209,
        "unit": "₹ Cr",
        "source": "Maruti FY financial results press release",
        "source_url": "https://www.marutisuzuki.com/corporate/media/press-releases/2024/april/maruti-suzuki-announces-financial-results-for-fy2023-24",
        "last_updated": "2026-05-12"
      }
    },
    "FY25": {
      "sales_volume_total": {
        "value": 2127844,
        "unit": "units",
        "source": "Maruti monthly sales press release",
        "source_url": "https://www.marutisuzuki.com/corporate/media/press-releases/2025/april/maruti-suzuki-sales-in-march-2025",
        "last_updated": "2026-05-12"
      },
      "sales_volume_domestic": {
        "value": 1795259,
        "unit": "units",
        "source": "Maruti monthly sales press release",
        "source_url": "https://www.marutisuzuki.com/corporate/media/press-releases/2025/april/maruti-suzuki-sales-in-march-2025",
        "last_updated": "2026-05-12"
      },
      "sales_volume_export": {
        "value": 332585,
        "unit": "units",
        "source": "Maruti monthly sales press release",
        "source_url": "https://www.marutisuzuki.com/corporate/media/press-releases/2025/april/maruti-suzuki-sales-in-march-2025",
        "last_updated": "2026-05-12"
      },
      "net_sales_cr": {
        "value": 145115,
        "unit": "₹ Cr",
        "source": "Maruti FY financial results press release",
        "source_url": "https://www.marutisuzuki.com/corporate/media/press-releases/2025/april/maruti-suzuki-announces-financial-results-for-fy2024-25",
        "last_updated": "2026-05-12"
      },
      "pat_cr": {
        "value": 13955,
        "unit": "₹ Cr",
        "source": "Maruti FY financial results press release",
        "source_url": "https://www.marutisuzuki.com/corporate/media/press-releases/2025/april/maruti-suzuki-announces-financial-results-for-fy2024-25",
        "last_updated": "2026-05-12"
      }
    },
    "Screener": {
      "fetched_at": "2026-05-12T11:29:03.822Z",
      "source_url": "https://www.screener.in/company/MARUTI/consolidated/",
      "basis": "Maruti Suzuki India consolidated annual P&L + cash flow",
      "by_fy": {
        "FY15": {
          "sales_cr": 50801,
          "expenses_cr": 43909,
          "ebitda_cr": 6892,
          "ebitda_margin_pct": 14,
          "interest_cr": 218,
          "depreciation_cr": 2515,
          "pbt_cr": 4976,
          "tax_pct": 24,
          "pat_cr": 3809,
          "equity_capital_cr": 151,
          "reserves_cr": 24167,
          "borrowings_cr": 666,
          "fixed_assets_cr": 12490,
          "investments_cr": 13298,
          "total_assets_cr": 34477,
          "cfo_cr": 6449,
          "investing_cr": -4491,
          "cff_cr": -2004
        },
        "FY16": {
          "sales_cr": 57589,
          "expenses_cr": 48565,
          "ebitda_cr": 9024,
          "ebitda_margin_pct": 16,
          "interest_cr": 82,
          "depreciation_cr": 2822,
          "pbt_cr": 7585,
          "tax_pct": 28,
          "pat_cr": 5497,
          "equity_capital_cr": 151,
          "reserves_cr": 30465,
          "borrowings_cr": 231,
          "fixed_assets_cr": 12530,
          "investments_cr": 20676,
          "total_assets_cr": 42726,
          "cfo_cr": 8482,
          "investing_cr": -7230,
          "cff_cr": -1237
        },
        "FY17": {
          "sales_cr": 68085,
          "expenses_cr": 57664,
          "ebitda_cr": 10421,
          "ebitda_margin_pct": 15,
          "interest_cr": 89,
          "depreciation_cr": 2604,
          "pbt_cr": 10127,
          "tax_pct": 26,
          "pat_cr": 7511,
          "equity_capital_cr": 151,
          "reserves_cr": 36924,
          "borrowings_cr": 484,
          "fixed_assets_cr": 13311,
          "investments_cr": 29151,
          "total_assets_cr": 51960,
          "cfo_cr": 10282,
          "investing_cr": -9173,
          "cff_cr": -1129
        },
        "FY18": {
          "sales_cr": 79809,
          "expenses_cr": 67692,
          "ebitda_cr": 12118,
          "ebitda_margin_pct": 15,
          "interest_cr": 346,
          "depreciation_cr": 2760,
          "pbt_cr": 11167,
          "tax_pct": 29,
          "pat_cr": 7881,
          "equity_capital_cr": 151,
          "reserves_cr": 42408,
          "borrowings_cr": 121,
          "fixed_assets_cr": 13389,
          "investments_cr": 36123,
          "total_assets_cr": 60248,
          "cfo_cr": 11788,
          "investing_cr": -8302,
          "cff_cr": -3436
        },
        "FY19": {
          "sales_cr": 86068,
          "expenses_cr": 75012,
          "ebitda_cr": 11056,
          "ebitda_margin_pct": 13,
          "interest_cr": 76,
          "depreciation_cr": 3021,
          "pbt_cr": 10624,
          "tax_pct": 28,
          "pat_cr": 7651,
          "equity_capital_cr": 151,
          "reserves_cr": 46941,
          "borrowings_cr": 160,
          "fixed_assets_cr": 15437,
          "investments_cr": 37504,
          "total_assets_cr": 63969,
          "cfo_cr": 6601,
          "investing_cr": -3540,
          "cff_cr": -2948
        },
        "FY20": {
          "sales_cr": 75660,
          "expenses_cr": 68305,
          "ebitda_cr": 7355,
          "ebitda_margin_pct": 10,
          "interest_cr": 134,
          "depreciation_cr": 3528,
          "pbt_cr": 7103,
          "tax_pct": 20,
          "pat_cr": 5678,
          "equity_capital_cr": 151,
          "reserves_cr": 49262,
          "borrowings_cr": 184,
          "fixed_assets_cr": 15744,
          "investments_cr": 37488,
          "total_assets_cr": 63628,
          "cfo_cr": 3496,
          "investing_cr": -557,
          "cff_cr": -3104
        },
        "FY21": {
          "sales_cr": 70372,
          "expenses_cr": 64961,
          "ebitda_cr": 5411,
          "ebitda_margin_pct": 8,
          "interest_cr": 102,
          "depreciation_cr": 3034,
          "pbt_cr": 5321,
          "tax_pct": 18,
          "pat_cr": 4389,
          "equity_capital_cr": 151,
          "reserves_cr": 52350,
          "borrowings_cr": 541,
          "fixed_assets_cr": 14989,
          "investments_cr": 42945,
          "total_assets_cr": 71376,
          "cfo_cr": 8856,
          "investing_cr": -7291,
          "cff_cr": -1545
        },
        "FY22": {
          "sales_cr": 88330,
          "expenses_cr": 82578,
          "ebitda_cr": 5752,
          "ebitda_margin_pct": 7,
          "interest_cr": 127,
          "depreciation_cr": 2789,
          "pbt_cr": 4697,
          "tax_pct": 17,
          "pat_cr": 3880,
          "equity_capital_cr": 151,
          "reserves_cr": 55182,
          "borrowings_cr": 426,
          "fixed_assets_cr": 13747,
          "investments_cr": 42035,
          "total_assets_cr": 74656,
          "cfo_cr": 1840,
          "investing_cr": -239,
          "cff_cr": -1607
        },
        "FY23": {
          "sales_cr": 117571,
          "expenses_cr": 106542,
          "ebitda_cr": 11029,
          "ebitda_margin_pct": 9,
          "interest_cr": 187,
          "depreciation_cr": 2826,
          "pbt_cr": 10323,
          "tax_pct": 20,
          "pat_cr": 8211,
          "equity_capital_cr": 151,
          "reserves_cr": 61640,
          "borrowings_cr": 1247,
          "fixed_assets_cr": 17830,
          "investments_cr": 49184,
          "total_assets_cr": 84597,
          "cfo_cr": 9251,
          "investing_cr": -8036,
          "cff_cr": -1213
        },
        "FY24": {
          "sales_cr": 141858,
          "expenses_cr": 123232,
          "ebitda_cr": 18626,
          "ebitda_margin_pct": 13,
          "interest_cr": 194,
          "depreciation_cr": 5256,
          "pbt_cr": 17424,
          "tax_pct": 23,
          "pat_cr": 13488,
          "equity_capital_cr": 157,
          "reserves_cr": 85479,
          "borrowings_cr": 119,
          "fixed_assets_cr": 27865,
          "investments_cr": 57296,
          "total_assets_cr": 115304,
          "cfo_cr": 16801,
          "investing_cr": -11865,
          "cff_cr": -4062
        },
        "FY25": {
          "sales_cr": 152913,
          "expenses_cr": 132689,
          "ebitda_cr": 20224,
          "ebitda_margin_pct": 13,
          "interest_cr": 194,
          "depreciation_cr": 5608,
          "pbt_cr": 19620,
          "tax_pct": 26,
          "pat_cr": 14500,
          "equity_capital_cr": 157,
          "reserves_cr": 96083,
          "borrowings_cr": 87,
          "fixed_assets_cr": 32983,
          "investments_cr": 66265,
          "total_assets_cr": 131971,
          "cfo_cr": 16136,
          "investing_cr": -14456,
          "cff_cr": -4155
        },
        "FY26": {
          "sales_cr": 183316,
          "expenses_cr": 161860,
          "ebitda_cr": 21456,
          "ebitda_margin_pct": 12,
          "interest_cr": 239,
          "depreciation_cr": 6742,
          "pbt_cr": 19118,
          "tax_pct": 23,
          "pat_cr": 14680,
          "equity_capital_cr": 157,
          "reserves_cr": 106999,
          "borrowings_cr": 102,
          "fixed_assets_cr": 34955,
          "investments_cr": 76838,
          "total_assets_cr": 148881,
          "cfo_cr": 19100,
          "investing_cr": -14734,
          "cff_cr": -4484
        }
      },
      "problems": []
    },
    "Tickertape": {
      "fetched_at": "2026-05-12T11:29:08.750Z",
      "source_url": "https://www.tickertape.in/stocks/maruti-suzuki-india-MARU",
      "by_fy": {},
      "problems": [
        "no BS sub-lines parsed"
      ]
    },
    "Moneycontrol": {
      "fetched_at": "2026-05-12T11:29:12.938Z",
      "source_url": "https://www.moneycontrol.com/financials/marutisuzukiindia/balance-sheetVI/MS24",
      "by_fy": {},
      "problems": [
        "no BS sub-lines parsed"
      ]
    }
  },
  "Hyundai": {
    "FY24": {
      "ebitda_cr": {
        "value": 9133,
        "unit": "₹ Cr",
        "scope": "Standalone",
        "source": "Hyundai Q4 audited standalone results PR",
        "source_url": "https://www.hyundai.com/content/dam/hyundai/in/en/data/investor-relations/annoucements/pressrelease-audited-standalone.pdf",
        "last_updated": "2026-05-12"
      },
      "export_volume": {
        "value": 599,
        "unit": "units",
        "scope": "Standalone",
        "source": "Hyundai Q4 audited standalone results PR",
        "source_url": "https://www.hyundai.com/content/dam/hyundai/in/en/data/investor-relations/annoucements/pressrelease-audited-standalone.pdf",
        "last_updated": "2026-05-06"
      },
      "revenue_cr": {
        "value": 69829,
        "unit": "₹ Cr",
        "scope": "Standalone",
        "source": "Hyundai Q4 audited standalone results PR",
        "source_url": "https://www.hyundai.com/content/dam/hyundai/in/en/data/investor-relations/annoucements/pressrelease-audited-standalone.pdf",
        "last_updated": "2026-05-12"
      },
      "ebitda_margin_pct": {
        "value": 13.1,
        "unit": "%",
        "scope": "Standalone",
        "source": "Hyundai Q4 audited standalone results PR",
        "source_url": "https://www.hyundai.com/content/dam/hyundai/in/en/data/investor-relations/annoucements/pressrelease-audited-standalone.pdf",
        "last_updated": "2026-05-12"
      },
      "pat_cr": {
        "value": 6060,
        "unit": "₹ Cr",
        "scope": "Standalone",
        "source": "Hyundai Q4 audited standalone results PR",
        "source_url": "https://www.hyundai.com/content/dam/hyundai/in/en/data/investor-relations/annoucements/pressrelease-audited-standalone.pdf",
        "last_updated": "2026-05-12"
      }
    },
    "FY25": {
      "ebitda_cr": {
        "value": 8954,
        "unit": "₹ Cr",
        "scope": "Standalone",
        "source": "Hyundai Q4 audited standalone results PR",
        "source_url": "https://www.hyundai.com/content/dam/hyundai/in/en/data/investor-relations/annoucements/pressrelease-audited-standalone.pdf",
        "last_updated": "2026-05-12"
      },
      "export_volume": {
        "value": 163000,
        "unit": "units",
        "scope": "Standalone",
        "source": "Hyundai Q4 audited standalone results PR",
        "source_url": "https://www.hyundai.com/content/dam/hyundai/in/en/data/investor-relations/annoucements/pressrelease-audited-standalone.pdf",
        "last_updated": "2026-05-12"
      },
      "suv_mix_pct": {
        "value": 68.5,
        "unit": "%",
        "scope": "Standalone",
        "source": "Hyundai Q4 audited standalone results PR",
        "source_url": "https://www.hyundai.com/content/dam/hyundai/in/en/data/investor-relations/annoucements/pressrelease-audited-standalone.pdf",
        "last_updated": "2026-05-12"
      },
      "revenue_cr": {
        "value": 69193,
        "unit": "₹ Cr",
        "scope": "Standalone",
        "source": "Hyundai Q4 audited standalone results PR",
        "source_url": "https://www.hyundai.com/content/dam/hyundai/in/en/data/investor-relations/annoucements/pressrelease-audited-standalone.pdf",
        "last_updated": "2026-05-12"
      },
      "ebitda_margin_pct": {
        "value": 12.9,
        "unit": "%",
        "scope": "Standalone",
        "source": "Hyundai Q4 audited standalone results PR",
        "source_url": "https://www.hyundai.com/content/dam/hyundai/in/en/data/investor-relations/annoucements/pressrelease-audited-standalone.pdf",
        "last_updated": "2026-05-12"
      },
      "pat_cr": {
        "value": 5640,
        "unit": "₹ Cr",
        "scope": "Standalone",
        "source": "Hyundai Q4 audited standalone results PR",
        "source_url": "https://www.hyundai.com/content/dam/hyundai/in/en/data/investor-relations/annoucements/pressrelease-audited-standalone.pdf",
        "last_updated": "2026-05-12"
      },
      "domestic_volume": {
        "value": 599000,
        "unit": "units",
        "scope": "Standalone",
        "source": "Hyundai Q4 audited standalone results PR",
        "source_url": "https://www.hyundai.com/content/dam/hyundai/in/en/data/investor-relations/annoucements/pressrelease-audited-standalone.pdf",
        "last_updated": "2026-05-12"
      }
    },
    "Tijori": {
      "fetched_at": "2026-05-12T11:28:59.952Z",
      "source_url": "https://www.tijorifinance.com/company/hyundai-motor-india-ltd/",
      "by_fy": {},
      "problems": [
        "no volume row found",
        "no parseable yearly values"
      ]
    },
    "Screener": {
      "fetched_at": "2026-05-12T11:29:05.048Z",
      "source_url": "https://www.screener.in/company/HYUNDAI/",
      "basis": "Hyundai Motor India standalone P&L + cash flow (per Screener; pre-FY18 from DRHP bootstrap)",
      "by_fy": {
        "FY19": {
          "sales_cr": 43258,
          "expenses_cr": 38415,
          "ebitda_cr": 4843,
          "ebitda_margin_pct": 11,
          "interest_cr": 128,
          "depreciation_cr": 1410,
          "pbt_cr": 3968,
          "tax_pct": 35,
          "pat_cr": 2582,
          "equity_capital_cr": 813,
          "reserves_cr": 12938,
          "borrowings_cr": 1069,
          "total_assets_cr": 23078,
          "cfo_cr": 4270,
          "investing_cr": -1781,
          "cff_cr": -465
        },
        "FY20": {
          "sales_cr": 42979,
          "expenses_cr": 38694,
          "ebitda_cr": 4285,
          "ebitda_margin_pct": 10,
          "interest_cr": 156,
          "depreciation_cr": 1616,
          "pbt_cr": 3213,
          "tax_pct": 27,
          "pat_cr": 2355,
          "equity_capital_cr": 813,
          "reserves_cr": 12467,
          "borrowings_cr": 1098,
          "total_assets_cr": 22331,
          "cfo_cr": 4072,
          "investing_cr": -2357,
          "cff_cr": -2898
        },
        "FY21": {
          "sales_cr": 40674,
          "expenses_cr": 36497,
          "ebitda_cr": 4177,
          "ebitda_margin_pct": 10,
          "interest_cr": 165,
          "depreciation_cr": 1944,
          "pbt_cr": 2493,
          "tax_pct": 26,
          "pat_cr": 1847,
          "equity_capital_cr": 813,
          "reserves_cr": 14318,
          "borrowings_cr": 1354,
          "total_assets_cr": 26498,
          "cfo_cr": 5365,
          "investing_cr": -2157,
          "cff_cr": 143
        },
        "FY22": {
          "sales_cr": 47043,
          "expenses_cr": 41628,
          "ebitda_cr": 5415,
          "ebitda_margin_pct": 12,
          "interest_cr": 132,
          "depreciation_cr": 2136,
          "pbt_cr": 3723,
          "tax_pct": 23,
          "pat_cr": 2862,
          "equity_capital_cr": 813,
          "reserves_cr": 15823,
          "borrowings_cr": 1175,
          "total_assets_cr": 28084,
          "cfo_cr": 5081,
          "investing_cr": -875,
          "cff_cr": -1662
        },
        "FY23": {
          "sales_cr": 59761,
          "expenses_cr": 52308,
          "ebitda_cr": 7454,
          "ebitda_margin_pct": 12,
          "interest_cr": 142,
          "depreciation_cr": 2155,
          "pbt_cr": 6269,
          "tax_pct": 26,
          "pat_cr": 4654,
          "equity_capital_cr": 813,
          "reserves_cr": 18965,
          "borrowings_cr": 1188,
          "total_assets_cr": 34159,
          "cfo_cr": 6476,
          "investing_cr": -1370,
          "cff_cr": -1578
        },
        "FY24": {
          "sales_cr": 68539,
          "expenses_cr": 59623,
          "ebitda_cr": 8915,
          "ebitda_margin_pct": 13,
          "interest_cr": 158,
          "depreciation_cr": 2172,
          "pbt_cr": 8095,
          "tax_pct": 26,
          "pat_cr": 5954,
          "equity_capital_cr": 813,
          "reserves_cr": 9472,
          "borrowings_cr": 832,
          "total_assets_cr": 25654,
          "cfo_cr": 9113,
          "investing_cr": -9814,
          "cff_cr": -15929
        },
        "FY25": {
          "sales_cr": 67654,
          "expenses_cr": 58943,
          "ebitda_cr": 8710,
          "ebitda_margin_pct": 13,
          "interest_cr": 127,
          "depreciation_cr": 2075,
          "pbt_cr": 7391,
          "tax_pct": 26,
          "pat_cr": 5492,
          "equity_capital_cr": 813,
          "reserves_cr": 14954,
          "borrowings_cr": 847,
          "total_assets_cr": 29372,
          "cfo_cr": 4251,
          "investing_cr": -322,
          "cff_cr": -62
        },
        "FY26": {
          "sales_cr": 68991,
          "expenses_cr": 60598,
          "ebitda_cr": 8392,
          "ebitda_margin_pct": 12,
          "interest_cr": 106,
          "depreciation_cr": 2154,
          "pbt_cr": 7082,
          "tax_pct": 25,
          "pat_cr": 5322,
          "equity_capital_cr": 813,
          "reserves_cr": 18558,
          "borrowings_cr": 1082,
          "total_assets_cr": 33521,
          "cfo_cr": 7174,
          "investing_cr": -2022,
          "cff_cr": -1587
        }
      },
      "problems": []
    },
    "Moneycontrol": {
      "fetched_at": "2026-05-12T11:29:13.256Z",
      "source_url": "https://www.moneycontrol.com/financials/hyundaimotorindia/balance-sheetVI/HMI01",
      "by_fy": {},
      "problems": [
        "no BS sub-lines parsed"
      ]
    }
  },
  "M&M": {
    "FY24": {
      "consol_pat_cr": {
        "value": 11269,
        "unit": "₹ Cr",
        "scope": "Consolidated",
        "source": "M&M Q4 + FY results PR",
        "source_url": "https://www.mahindra.com/news-room/press-release/mm-results-q4-fy24-and-fy24",
        "last_updated": "2026-05-06"
      },
      "auto_revenue_cr": {
        "value": 76156,
        "unit": "₹ Cr",
        "scope": "Auto segment",
        "source": "M&M Q4 + FY results PR",
        "source_url": "https://www.mahindra.com/news-room/press-release/mm-results-q4-fy24-and-fy24",
        "last_updated": "2026-05-12"
      }
    },
    "FY25": {
      "consol_revenue_cr": {
        "value": 159211,
        "unit": "₹ Cr",
        "scope": "Consolidated",
        "source": "M&M Q4 + FY results PR",
        "source_url": "https://www.mahindra.com/news-room/press-release/en/mm-results-q4-fy25-and-fy25",
        "last_updated": "2026-05-12"
      },
      "consol_pat_cr": {
        "value": 12929,
        "unit": "₹ Cr",
        "scope": "Consolidated",
        "source": "M&M Q4 + FY results PR",
        "source_url": "https://www.mahindra.com/news-room/press-release/en/mm-results-q4-fy25-and-fy25",
        "last_updated": "2026-05-12"
      },
      "auto_revenue_cr": {
        "value": 90825,
        "unit": "₹ Cr",
        "scope": "Auto segment",
        "source": "M&M Q4 + FY results PR",
        "source_url": "https://www.mahindra.com/news-room/press-release/en/mm-results-q4-fy25-and-fy25",
        "last_updated": "2026-05-12"
      },
      "suv_volume": {
        "value": 551487,
        "unit": "units",
        "scope": "Auto segment",
        "source": "M&M monthly auto sales PR",
        "source_url": "https://www.mahindra.com/news-room/press-release/en/mahindra-auto-sells-48048-SUVs-a-growth-of-18-percents-and-total-volumes-of-83894-a-growth-of-23-percents-in-march-2025",
        "last_updated": "2026-05-12"
      }
    },
    "Screener": {
      "fetched_at": "2026-05-12T11:28:59.111Z",
      "source_url": "https://www.screener.in/company/M%26M/consolidated/",
      "by_fy": {
        "FY15": {
          "sales_cr": 71448,
          "expenses_cr": 62655,
          "ebitda_cr": 8793,
          "ebitda_margin_pct": 12,
          "interest_cr": 3157,
          "depreciation_cr": 2124,
          "pbt_cr": 4313,
          "tax_pct": 40,
          "pat_cr": 3381,
          "equity_capital_cr": 296,
          "reserves_cr": 25561,
          "borrowings_cr": 37911,
          "total_liab_cr": 94376,
          "fixed_assets_cr": 19047,
          "investments_cr": 10027,
          "total_assets_cr": 94376,
          "working_capital_days": -5,
          "roce_pct": 11,
          "cfo_cr": 1055,
          "investing_cr": -4357,
          "cff_cr": 1669,
          "net_cash_cr": -1633
        },
        "FY16": {
          "sales_cr": 75841,
          "expenses_cr": 65759,
          "ebitda_cr": 10082,
          "ebitda_margin_pct": 13,
          "interest_cr": 3368,
          "depreciation_cr": 2442,
          "pbt_cr": 5672,
          "tax_pct": 37,
          "pat_cr": 3554,
          "equity_capital_cr": 270,
          "reserves_cr": 26222,
          "borrowings_cr": 41553,
          "total_liab_cr": 99852,
          "fixed_assets_cr": 20585,
          "investments_cr": 11603,
          "total_assets_cr": 99852,
          "working_capital_days": -3,
          "roce_pct": 13,
          "cfo_cr": 2385,
          "investing_cr": -5506,
          "cff_cr": 2967,
          "net_cash_cr": -154,
          "revenue_growth_pct": 6.1
        },
        "FY17": {
          "sales_cr": 83773,
          "expenses_cr": 73038,
          "ebitda_cr": 10735,
          "ebitda_margin_pct": 13,
          "interest_cr": 3648,
          "depreciation_cr": 2813,
          "pbt_cr": 6350,
          "tax_pct": 36,
          "pat_cr": 4051,
          "equity_capital_cr": 311,
          "reserves_cr": 29467,
          "borrowings_cr": 48762,
          "total_liab_cr": 113835,
          "fixed_assets_cr": 20989,
          "investments_cr": 14662,
          "total_assets_cr": 113835,
          "working_capital_days": -2,
          "roce_pct": 12,
          "cfo_cr": 183,
          "investing_cr": -5875,
          "cff_cr": 6108,
          "net_cash_cr": 416,
          "revenue_growth_pct": 10.5
        },
        "FY18": {
          "sales_cr": 92094,
          "expenses_cr": 78868,
          "ebitda_cr": 13226,
          "ebitda_margin_pct": 14,
          "interest_cr": 3987,
          "depreciation_cr": 3280,
          "pbt_cr": 10326,
          "tax_pct": 23,
          "pat_cr": 7958,
          "equity_capital_cr": 543,
          "reserves_cr": 36232,
          "borrowings_cr": 55898,
          "total_liab_cr": 136369,
          "fixed_assets_cr": 26182,
          "investments_cr": 16018,
          "total_assets_cr": 136369,
          "working_capital_days": -8,
          "roce_pct": 13,
          "cfo_cr": 682,
          "investing_cr": -5467,
          "cff_cr": 6314,
          "net_cash_cr": 1529,
          "revenue_growth_pct": 9.9
        },
        "FY19": {
          "sales_cr": 104721,
          "expenses_cr": 89514,
          "ebitda_cr": 15207,
          "ebitda_margin_pct": 15,
          "interest_cr": 5021,
          "depreciation_cr": 3991,
          "pbt_cr": 8871,
          "tax_pct": 32,
          "pat_cr": 6017,
          "equity_capital_cr": 544,
          "reserves_cr": 39439,
          "borrowings_cr": 70848,
          "total_liab_cr": 161889,
          "fixed_assets_cr": 28983,
          "investments_cr": 18268,
          "total_assets_cr": 161889,
          "working_capital_days": -14,
          "roce_pct": 12,
          "cfo_cr": -4347,
          "investing_cr": -7174,
          "cff_cr": 13194,
          "net_cash_cr": 1672,
          "revenue_growth_pct": 13.7
        },
        "FY20": {
          "sales_cr": 75382,
          "expenses_cr": 65224,
          "ebitda_cr": 10158,
          "ebitda_margin_pct": 13,
          "interest_cr": 6021,
          "depreciation_cr": 3367,
          "pbt_cr": 1655,
          "tax_pct": 119,
          "pat_cr": -321,
          "equity_capital_cr": 554,
          "reserves_cr": 39415,
          "borrowings_cr": 82092,
          "total_liab_cr": 165716,
          "fixed_assets_cr": 29689,
          "investments_cr": 19210,
          "total_assets_cr": 165716,
          "working_capital_days": -20,
          "roce_pct": 7,
          "cfo_cr": -1457,
          "investing_cr": -6870,
          "cff_cr": 6933,
          "net_cash_cr": -1394,
          "revenue_growth_pct": -28
        },
        "FY21": {
          "sales_cr": 74278,
          "expenses_cr": 62791,
          "ebitda_cr": 11487,
          "ebitda_margin_pct": 15,
          "interest_cr": 6102,
          "depreciation_cr": 3378,
          "pbt_cr": 3158,
          "tax_pct": 52,
          "pat_cr": 1512,
          "equity_capital_cr": 555,
          "reserves_cr": 41027,
          "borrowings_cr": 80625,
          "total_liab_cr": 164968,
          "fixed_assets_cr": 21380,
          "investments_cr": 28778,
          "total_assets_cr": 164968,
          "working_capital_days": -11,
          "roce_pct": 8,
          "cfo_cr": 17909,
          "investing_cr": -19686,
          "cff_cr": 406,
          "net_cash_cr": -1370,
          "revenue_growth_pct": -1.5
        },
        "FY22": {
          "sales_cr": 90171,
          "expenses_cr": 75488,
          "ebitda_cr": 14683,
          "ebitda_margin_pct": 16,
          "interest_cr": 5018,
          "depreciation_cr": 3508,
          "pbt_cr": 9362,
          "tax_pct": 23,
          "pat_cr": 7253,
          "equity_capital_cr": 556,
          "reserves_cr": 46567,
          "borrowings_cr": 77605,
          "total_liab_cr": 172388,
          "fixed_assets_cr": 26018,
          "investments_cr": 30060,
          "total_assets_cr": 172388,
          "working_capital_days": -13,
          "roce_pct": 11,
          "cfo_cr": 9248,
          "investing_cr": -3252,
          "cff_cr": -5883,
          "net_cash_cr": 113,
          "revenue_growth_pct": 21.4
        },
        "FY23": {
          "sales_cr": 121269,
          "expenses_cr": 100983,
          "ebitda_cr": 20285,
          "ebitda_margin_pct": 17,
          "interest_cr": 5830,
          "depreciation_cr": 4357,
          "pbt_cr": 14060,
          "tax_pct": 19,
          "pat_cr": 11374,
          "equity_capital_cr": 557,
          "reserves_cr": 55809,
          "borrowings_cr": 92247,
          "total_liab_cr": 204283,
          "fixed_assets_cr": 27140,
          "investments_cr": 35272,
          "total_assets_cr": 204283,
          "working_capital_days": -14,
          "roce_pct": 13,
          "cfo_cr": -7074,
          "investing_cr": -8866,
          "cff_cr": 15946,
          "net_cash_cr": 6,
          "revenue_growth_pct": 34.5
        },
        "FY24": {
          "sales_cr": 139078,
          "expenses_cr": 114186,
          "ebitda_cr": 24892,
          "ebitda_margin_pct": 18,
          "interest_cr": 7488,
          "depreciation_cr": 4724,
          "pbt_cr": 15978,
          "tax_pct": 23,
          "pat_cr": 12270,
          "equity_capital_cr": 557,
          "reserves_cr": 65633,
          "borrowings_cr": 108647,
          "total_liab_cr": 234722,
          "fixed_assets_cr": 28129,
          "investments_cr": 35208,
          "total_assets_cr": 234722,
          "working_capital_days": -8,
          "roce_pct": 14,
          "cfo_cr": -5630,
          "investing_cr": -5615,
          "cff_cr": 12281,
          "net_cash_cr": 1037,
          "revenue_growth_pct": 14.7
        },
        "FY25": {
          "sales_cr": 159211,
          "expenses_cr": 128693,
          "ebitda_cr": 30518,
          "ebitda_margin_pct": 19,
          "interest_cr": 9083,
          "depreciation_cr": 6074,
          "pbt_cr": 19080,
          "tax_pct": 26,
          "pat_cr": 14073,
          "equity_capital_cr": 558,
          "reserves_cr": 76481,
          "borrowings_cr": 129025,
          "total_liab_cr": 276013,
          "fixed_assets_cr": 34636,
          "investments_cr": 41309,
          "total_assets_cr": 276013,
          "working_capital_days": -14,
          "roce_pct": 14,
          "cfo_cr": 3176,
          "investing_cr": -18616,
          "cff_cr": 15834,
          "net_cash_cr": 394,
          "revenue_growth_pct": 14.5
        },
        "FY26": {
          "sales_cr": 198639,
          "expenses_cr": 161077,
          "ebitda_cr": 37561,
          "ebitda_margin_pct": 19,
          "interest_cr": 9591,
          "depreciation_cr": 7322,
          "pbt_cr": 25185,
          "tax_pct": 26,
          "pat_cr": 18622,
          "equity_capital_cr": 559,
          "reserves_cr": 92538,
          "borrowings_cr": 133963,
          "total_liab_cr": 317635,
          "fixed_assets_cr": 43831,
          "investments_cr": 40324,
          "total_assets_cr": 317635,
          "working_capital_days": -2,
          "roce_pct": 15,
          "cfo_cr": 11657,
          "investing_cr": -17707,
          "cff_cr": 5391,
          "net_cash_cr": -659,
          "revenue_growth_pct": 24.8
        }
      },
      "problems": []
    },
    "Tijori": {
      "fetched_at": "2026-05-12T11:29:00.912Z",
      "source_url": "https://www.tijorifinance.com/company/mahindra-and-mahindra-ltd/",
      "by_fy": {},
      "problems": [
        "no volume row found",
        "no parseable yearly values"
      ]
    },
    "Moneycontrol": {
      "fetched_at": "2026-05-12T11:29:13.586Z",
      "source_url": "https://www.moneycontrol.com/financials/mahindramahindra/balance-sheetVI/MM",
      "by_fy": {},
      "problems": [
        "no BS sub-lines parsed"
      ]
    }
  },
  "Tata Motors PV": {
    "FY24": {
      "pv_revenue_cr": {
        "value": 52353,
        "unit": "₹ Cr",
        "scope": "Tata PV segment",
        "source": "Tata Motors Q4/FY results PR",
        "source_url": "https://www.tatamotors.com/press-releases/tata-motors-consolidated-q4-fy24-results/",
        "last_updated": "2026-05-12"
      },
      "consol_revenue_cr": {
        "value": 437900,
        "unit": "₹ Cr",
        "scope": "Consolidated",
        "source": "Tata Motors Q4/FY results PR",
        "source_url": "https://www.tatamotors.com/press-releases/tata-motors-consolidated-q4-fy24-results/",
        "last_updated": "2026-05-12"
      },
      "consol_pat_cr": {
        "value": 31800,
        "unit": "₹ Cr",
        "scope": "Consolidated",
        "source": "Tata Motors Q4/FY results PR",
        "source_url": "https://www.tatamotors.com/press-releases/tata-motors-consolidated-q4-fy24-results/",
        "last_updated": "2026-05-12"
      },
      "pv_ebitda_margin": {
        "value": 6.5,
        "unit": "%",
        "scope": "Tata PV segment",
        "source": "Tata Motors Q4/FY results PR",
        "source_url": "https://www.tatamotors.com/press-releases/tata-motors-consolidated-q4-fy24-results/",
        "last_updated": "2026-05-12"
      },
      "pv_ebit_margin": {
        "value": 2,
        "unit": "%",
        "scope": "Tata PV segment",
        "source": "Tata Motors Q4/FY results PR",
        "source_url": "https://www.tatamotors.com/press-releases/tata-motors-consolidated-q4-fy24-results/",
        "last_updated": "2026-05-12"
      }
    },
    "FY25": {
      "pv_volume_fy_total": {
        "value": 556263,
        "unit": "units",
        "scope": "Tata PV segment",
        "source": "Tata Motors Q4/FY sales PR",
        "source_url": "https://www.tatamotors.com/press-releases/tata-motors-registered-total-sales-of-252642-units-in-q4-fy25/",
        "last_updated": "2026-05-12"
      },
      "pv_revenue_cr": {
        "value": 48445,
        "unit": "₹ Cr",
        "scope": "Tata PV segment",
        "source": "Tata Motors Q4/FY results PR",
        "source_url": "https://www.tatamotors.com/press-releases/tata-motors-consolidated-q4-fy25-results/",
        "last_updated": "2026-05-12"
      },
      "pv_ebitda_margin": {
        "value": 6.9,
        "unit": "%",
        "scope": "Tata PV segment",
        "source": "Tata Motors Q4/FY results PR",
        "source_url": "https://www.tatamotors.com/press-releases/tata-motors-consolidated-q4-fy25-results/",
        "last_updated": "2026-05-12"
      },
      "pv_ebit_margin": {
        "value": 0.9,
        "unit": "%",
        "scope": "Tata PV segment",
        "source": "Tata Motors Q4/FY results PR",
        "source_url": "https://www.tatamotors.com/press-releases/tata-motors-consolidated-q4-fy25-results/",
        "last_updated": "2026-05-12"
      },
      "consol_revenue_cr": {
        "value": 439700,
        "unit": "₹ Cr",
        "scope": "Consolidated",
        "source": "Tata Motors Q4/FY results PR",
        "source_url": "https://www.tatamotors.com/press-releases/tata-motors-consolidated-q4-fy25-results/",
        "last_updated": "2026-05-12"
      },
      "consol_pat_cr": {
        "value": 28100,
        "unit": "₹ Cr",
        "scope": "Consolidated",
        "source": "Tata Motors Q4/FY results PR",
        "source_url": "https://www.tatamotors.com/press-releases/tata-motors-consolidated-q4-fy25-results/",
        "last_updated": "2026-05-12"
      }
    },
    "Tijori": {
      "fetched_at": "2026-05-12T11:29:01.867Z",
      "source_url": "https://www.tijorifinance.com/company/tata-motors-ltd/",
      "by_fy": {},
      "problems": [
        "no volume row found",
        "no parseable yearly values"
      ]
    },
    "Moneycontrol": {
      "fetched_at": "2026-05-12T11:29:13.910Z",
      "source_url": "https://www.moneycontrol.com/financials/tatamotors/balance-sheetVI/TM03",
      "by_fy": {},
      "problems": [
        "no BS sub-lines parsed"
      ]
    }
  }
}
